{
  "documentId": "dy8vjpzy4pts6ahh9e224s7b",
  "name": "Author",
  "code": "strapi-author",
  "description": "Authors can manage the content they have created.",
  "locale": null,
  "permissions": [
    {
      "documentId": "zjzlii9g2w4n6nmadjwndpx9",
      "action": "plugin::upload.assets.copy-link",
      "actionParameters": {},
      "subject": null,
      "properties": {},
      "conditions": [],
      "locale": null
    },
    {
      "documentId": "p40apcctmy7igd870jfpadwi",
      "action": "plugin::upload.assets.create",
      "actionParameters": {},
      "subject": null,
      "properties": {},
      "conditions": [],
      "locale": null
    },
    {
      "documentId": "aexu3dy1c0goo7gm9c7enty8",
      "action": "plugin::upload.assets.download",
      "actionParameters": {},
      "subject": null,
      "properties": {},
      "conditions": [],
      "locale": null
    },
    {
      "documentId": "gxvselh8w9azrjuiezarttau",
      "action": "plugin::upload.assets.update",
      "actionParameters": {},
      "subject": null,
      "properties": {},
      "conditions": [
        "admin::is-creator"
      ],
      "locale": null
    },
    {
      "documentId": "oe49akrwir8qhn0yhkncfocp",
      "action": "plugin::upload.configure-view",
      "actionParameters": {},
      "subject": null,
      "properties": {},
      "conditions": [],
      "locale": null
    },
    {
      "documentId": "q4l5sg9700xs575ez03b5cw3",
      "action": "plugin::upload.read",
      "actionParameters": {},
      "subject": null,
      "properties": {},
      "conditions": [
        "admin::is-creator"
      ],
      "locale": null
    }
  ]
}